smsAlert/__init__.py
smsAlert/smsAlert.py
smsAlert-1.0.1.dist-info/AUTHORS.rst
smsAlert-1.0.1.dist-info/LICENSE
smsAlert-1.0.1.dist-info/METADATA
smsAlert-1.0.1.dist-info/WHEEL
smsAlert-1.0.1.dist-info/top_level.txt
smsAlert-1.0.1.dist-info/RECORD
